s3sel/__init__.py
s3sel/cli.py
s3sel/files.py
s3sel/ui.py
s3sel/utils.py
s3sel-0.2.3.dist-info/METADATA
s3sel-0.2.3.dist-info/WHEEL
s3sel-0.2.3.dist-info/entry_points.txt
s3sel-0.2.3.dist-info/RECORD
