Metadata-Version: 2.3
Name: s3sel
Version: 0.2.3
Summary: A small tool for simple management of multiple .s3cfg files.
Project-URL: Homepage, https://github.com/dess1e/s3sel
Author-email: Andrii Stadnik <astadnik99@gmail.com>
Requires-Python: >=3.8
Requires-Dist: simple-term-menu==1.6.4
Requires-Dist: termcolor==2.4.0
